pyglobegl/__init__.py
pyglobegl/_static/index.js
pyglobegl/config.py
pyglobegl/geopandas.py
pyglobegl/images.py
pyglobegl/py.typed
pyglobegl/widget.py
pyglobegl-0.5.0.dist-info/WHEEL
pyglobegl-0.5.0.dist-info/METADATA
pyglobegl-0.5.0.dist-info/RECORD
