Metadata-Version: 2.3
Name: pyglobegl
Version: 0.5.0
Summary: anywidget wrapper for globe.gl
Keywords: anywidget,globe.gl,jupyter,marimo,webgl,widget,visualization
Author: Owen Lamont
Author-email: Owen Lamont <owenrlamont@gmail.com>
License: MIT License
Classifier: Development Status :: 2 - Pre-Alpha
Classifier: Intended Audience :: Developers
Classifier: Operating System :: OS Independent
Classifier: License :: OSI Approved :: MIT License
Classifier: Natural Language :: English
Classifier: Programming Language :: Python
Classifier: Programming Language :: Python :: 3
Classifier: Programming Language :: Python :: 3.10
Classifier: Programming Language :: Python :: 3.11
Classifier: Programming Language :: Python :: 3.12
Classifier: Programming Language :: Python :: 3.13
Classifier: Programming Language :: Python :: 3.14
Classifier: Programming Language :: Python :: 3 :: Only
Classifier: Programming Language :: Python :: Implementation :: CPython
Classifier: Typing :: Typed
Classifier: Topic :: Scientific/Engineering :: Visualization
Classifier: Topic :: Software Development :: Libraries
Requires-Dist: anywidget>=0.9.21
Requires-Dist: geojson-pydantic>=2.1.0
Requires-Dist: pillow>=12.1.0
Requires-Dist: pydantic>=2.12.5
Requires-Dist: traitlets>=5.14.3
Requires-Dist: geopandas>=1.1.2 ; extra == 'geopandas'
Requires-Dist: pandera>=0.28.1 ; extra == 'geopandas'
Requires-Dist: webcolors ; extra == 'geopandas'
Requires-Python: >=3.10
Project-URL: Repository, https://github.com/owenlamont/pyglobegl
Project-URL: Issues, https://github.com/owenlamont/pyglobegl/issues
Project-URL: Releases, https://github.com/owenlamont/pyglobegl/releases
Provides-Extra: geopandas
